{"cameraMode":{"drawMode":0,"name":"Shaded","section":"Shading Mode"},"sceneLighting":true,"audioPlay":false,"sceneViewState":{"showFog":true,"showMaterialUpdate":false,"showSkybox":true,"showFlares":true,"showImageEffects":true,"showParticleSystems":true},"in2DMode":false,"pivot":{"x":0.16936266422271729,"y":0.6399998664855957,"z":5.859902858734131},"rotation":{"x":-0.23981812596321107,"y":0.6368600726127625,"z":-0.21836251020431519,"w":-0.6994474530220032},"size":9.764883041381836,"orthographic":false}